pt/__init__.py
pt/main.py
pt/controllers/__init__.py
pt/controllers/base.py
pt/controllers/constants.py
pt/controllers/pivotal.py
pt/controllers/rich_uis.py
pt/controllers/utils.py
pt/core/__init__.py
pt/core/exc.py
pt/core/version.py
pt/ext/__init__.py
pt/plugins/__init__.py
pt/templates/__init__.py
pt/templates/command1.jinja2
pt/templates/pt/list.jinja2
pt/templates/pt/notifications.jinja2
pt_cli-0.0.2.dev20211020125402.dist-info/LICENSE.md
pt_cli-0.0.2.dev20211020125402.dist-info/METADATA
pt_cli-0.0.2.dev20211020125402.dist-info/WHEEL
pt_cli-0.0.2.dev20211020125402.dist-info/entry_points.txt
pt_cli-0.0.2.dev20211020125402.dist-info/top_level.txt
pt_cli-0.0.2.dev20211020125402.dist-info/RECORD
