Metadata-Version: 2.1
Name: pt-cli
Version: 0.0.2.dev20211020125402
Summary: It uses an pivotal tracker api and does lot of cool stuffs like creating tickets.
Home-page: https://github.com/rabinpoudyal/pt
Author: Rabin Poudyal
Author-email: rabinpoudyal1995@gmail.com
License: MIT
Platform: UNKNOWN
License-File: LICENSE.md
Requires-Dist: cement (==3.0.4)
Requires-Dist: jinja2
Requires-Dist: colorlog
Requires-Dist: requests
Requires-Dist: enquiries
Requires-Dist: pyyaml
Requires-Dist: rich
Requires-Dist: tabulate
